explorercmd/__init__.py
explorercmd/client.py
explorercmd/server.py
explorercmd-0.1.5.dist-info/licenses/LICENSE
explorercmd-0.1.5.dist-info/METADATA
explorercmd-0.1.5.dist-info/WHEEL
explorercmd-0.1.5.dist-info/entry_points.txt
explorercmd-0.1.5.dist-info/top_level.txt
explorercmd-0.1.5.dist-info/RECORD
