Metadata-Version: 2.4
Name: explorercmd
Version: 0.1.5
Summary: Remote file explorer client
Author-email: qDephelinTeq <secret@example.com>
Requires-Python: >=3.6
License-File: LICENSE
Dynamic: license-file
